Metadata-Version: 2.1
Name: SeleniumGridServer
Version: 0.0.2a4
Summary: ChokChaisak
Home-page: https://test.pypi.org/user/ChokChaisak/
Author: ChokChaisak
Author-email: ChokChaisak@gmail.com
License: ChokChaisak
Keywords: SeleniumGridServer
